{"about_citing.md":"C4WTtede","about_contributing.md":"Cj4sJLL7","about_development.md":"BNhDXKSZ","about_index.md":"RErhjToP","about_license.md":"C-sxqZLp","about_versions.md":"DQAwdIFc","examples_generated_actuator2d.md":"CD3n3Vme","examples_generated_actuator3d.md":"BYLuXGQp","examples_generated_backwardfacingstep2d.md":"DraVlWDI","examples_generated_backwardfacingstep3d.md":"BgA9wtfg","examples_generated_decayingturbulence2d.md":"horkE--s","examples_generated_decayingturbulence3d.md":"EjqwGm0K","examples_generated_kolmogorov2d.md":"DImOB89O","examples_generated_liddrivencavity2d.md":"DSj2Nmwf","examples_generated_liddrivencavity3d.md":"aT93ND46","examples_generated_multiactuator.md":"CmOQSt6p","examples_generated_planarmixing2d.md":"jQc8oZtM","examples_generated_planejets2d.md":"LSr_45au","examples_generated_rayleighbenard2d.md":"e9V48GUt","examples_generated_rayleighbenard3d.md":"B5zFiVkR","examples_generated_rayleightaylor2d.md":"Cd5pcCiZ","examples_generated_rayleightaylor3d.md":"TnGwMK3h","examples_generated_shearlayer2d.md":"CTwL6eNd","examples_generated_taylorgreenvortex2d.md":"DoaoOIRY","examples_generated_taylorgreenvortex3d.md":"Bx5VU-Ov","examples_index.md":"BtyE1xq2","getting_started.md":"BURYaRF9","index.md":"By5jaAKr","manual_closure.md":"BFeh0UIW","manual_differentiability.md":"CMFLeWZs","manual_gpu.md":"Br1egl19","manual_les.md":"WJSe4p3P","manual_ns.md":"BafUknCS","manual_operators.md":"C-CHmyGi","manual_precision.md":"BSFQG6kb","manual_pressure.md":"6EC6Htiv","manual_sciml.md":"DVfIvK8E","manual_setup.md":"BLyLLpKY","manual_solver.md":"DEo8uD95","manual_spatial.md":"BBmvt2np","manual_temperature.md":"DppKIcxz","manual_time.md":"DqvQaU2s","manual_utils.md":"ngTHxk5t","references.md":"dWtplpa3"}
